aneris/__init__.py
aneris/_io.py
aneris/cli.py
aneris/convenience.py
aneris/errors.py
aneris/grid.py
aneris/harmonize.py
aneris/methods.py
aneris/tutorial.py
aneris/utils.py
aneris/cmip6/__init__.py
aneris/cmip6/cmip6_utils.py
aneris/cmip6/driver.py
aneris/downscaling/__init__.py
aneris/downscaling/core.py
aneris/downscaling/data.py
aneris/downscaling/intensity_convergence.py
aneris/downscaling/methods.py
aneris_iamc-0.4.2.dist-info/LICENSE
aneris_iamc-0.4.2.dist-info/METADATA
aneris_iamc-0.4.2.dist-info/WHEEL
aneris_iamc-0.4.2.dist-info/entry_points.txt
aneris_iamc-0.4.2.dist-info/top_level.txt
aneris_iamc-0.4.2.dist-info/RECORD
