Metadata-Version: 2.1
Name: aneris-iamc
Version: 0.4.2
Summary: Harmonize Integrated Assessment Model Emissions Trajectories
Author-email: Matthew Gidden <matthew.gidden@gmail.com>, Jonas Hoersch <jonas.hoersch@climateanalytics.org>
License: Apache License 2.0
Classifier: Programming Language :: Python :: 3
Classifier: License :: OSI Approved :: Apache Software License
Requires-Python: >=3.10
License-File: LICENSE
Requires-Dist: numpy
Requires-Dist: pandas>=1.1
Requires-Dist: PyYAML
Requires-Dist: xlrd>=2.0
Requires-Dist: openpyxl
Requires-Dist: matplotlib
Requires-Dist: pyomo>=5
Requires-Dist: pandas-indexing>=0.4.0
Requires-Dist: pycountry
Provides-Extra: deploy
Requires-Dist: twine; extra == "deploy"
Requires-Dist: setuptools; extra == "deploy"
Requires-Dist: wheel; extra == "deploy"
Provides-Extra: convenience
Requires-Dist: pyam-iamc; extra == "convenience"
Provides-Extra: test
Requires-Dist: coverage; extra == "test"
Requires-Dist: pytest; extra == "test"
Requires-Dist: pytest-cov; extra == "test"
Requires-Dist: hypothesis; extra == "test"
Requires-Dist: pooch; extra == "test"
Requires-Dist: nbformat; extra == "test"
Requires-Dist: nbconvert; extra == "test"
Provides-Extra: units
Requires-Dist: openscm-units; extra == "units"
Provides-Extra: docs
Requires-Dist: sphinx; extra == "docs"
Requires-Dist: sphinxcontrib-bibtex; extra == "docs"
Requires-Dist: sphinxcontrib-programoutput; extra == "docs"
Requires-Dist: sphinxcontrib-exceltable; extra == "docs"
Requires-Dist: sphinx-gallery; extra == "docs"
Requires-Dist: nbsphinx; extra == "docs"
Requires-Dist: numpydoc; extra == "docs"
Requires-Dist: nbformat; extra == "docs"
Requires-Dist: pillow; extra == "docs"
Provides-Extra: lint
Requires-Dist: black; extra == "lint"
Requires-Dist: ruff; extra == "lint"
Provides-Extra: geo
Requires-Dist: ptolemy-iamc; extra == "geo"
Requires-Dist: pycountry; extra == "geo"
Requires-Dist: xarray; extra == "geo"
Requires-Dist: dask; extra == "geo"
